uploadgram/__init__.py
uploadgram/config.py
uploadgram/get_config.py
uploadgram/humanbytes.py
uploadgram/progress.py
uploadgram/run_shell_command.py
uploadgram/shell.py
uploadgram/take_screen_shot.py
uploadgram/time_formatter.py
uploadgram/upload.py
uploadgram/uploadgram.py
uploadgram-0.3.4.dist-info/LICENSE
uploadgram-0.3.4.dist-info/METADATA
uploadgram-0.3.4.dist-info/WHEEL
uploadgram-0.3.4.dist-info/entry_points.txt
uploadgram-0.3.4.dist-info/RECORD
